hetznerinv/__init__.py
hetznerinv/cli.py
hetznerinv/cmd/__init__.py
hetznerinv/cmd/default_config.py
hetznerinv/cmd/generate.py
hetznerinv/cmd/list.py
hetznerinv/cmd/sync.py
hetznerinv/cmd/version.py
hetznerinv/config.py
hetznerinv/generate_inventory.py
hetznerinv/hetzner/__init__.py
hetznerinv/hetzner/failover.py
hetznerinv/hetzner/rdns.py
hetznerinv/hetzner/reset.py
hetznerinv/hetzner/robot.py
hetznerinv/hetzner/server.py
hetznerinv/hetzner/tests/__init__.py
hetznerinv/hetzner/tests/test_util_addr.py
hetznerinv/hetzner/util/__init__.py
hetznerinv/hetzner/util/addr.py
hetznerinv/hetzner/util/http.py
hetznerinv/hetzner/util/scraping.py
hetznerinv/hetzner/vswitch.py
hetznerinv/version.py
hetznerinv-0.3.3.dist-info/WHEEL
hetznerinv-0.3.3.dist-info/entry_points.txt
hetznerinv-0.3.3.dist-info/METADATA
hetznerinv-0.3.3.dist-info/RECORD
