Metadata-Version: 2.3
Name: hetznerinv
Version: 0.3.3
Summary: 
Author: ant31
Author-email: ant31 <2t.antoine@gmail.com>
License: Apache-2.0
Classifier: Programming Language :: Python :: 3
Classifier: Programming Language :: Python :: 3.12
Classifier: Programming Language :: Python :: 3.13
Classifier: Programming Language :: Python :: 3.14
Requires-Dist: pydantic
Requires-Dist: typer
Requires-Dist: pyyaml
Requires-Dist: typing-extensions
Requires-Dist: pyyaml
Requires-Dist: ant31box>=0.2.3
Requires-Dist: click<8.2.0
Requires-Dist: hcloud>=2.5.1,<3.0.0
Requires-Dist: rich>=14.0.0,<15.0.0
Requires-Python: >=3.12, <4
